[{"avl_location": {"vehicle": {"id": "b73A", "id2": "G9NSJ6703F6J", "fleet": "Heavy", "type": "Attenuator", "sub_type": "Attenuator (ATMA)"}, "position": {"latitude": 39.2692719, "longitude": -103.715607, "bearing": null, "speed": 0.0, "odometer": null}, "confidence": null, "current_status": {"state": "Active", "info": "Parked"}, "additional_info": [], "source": {"name": "Geotab", "collection_timestamp": "2022-06-22T14:16:33Z"}}, "rtdh_message_id": "510d8f00-2aaf-4ea3-bd1d-39495f29ec79", "rtdh_timestamp": "2022-06-22T14:17:27Z"}]